ania/__init__.py
ania/api/__init__.py
ania/app.py
ania/get_servers.py
ania/search_anime.py
ania/select_anime.py
ania/select_episode.py
ania/ui.py
ania/utils.py
ania/web_player/__init__.py
ania/web_player/templates/index.html
ania-1.0.0.dist-info/LICENSE
ania-1.0.0.dist-info/METADATA
ania-1.0.0.dist-info/WHEEL
ania-1.0.0.dist-info/entry_points.txt
ania-1.0.0.dist-info/RECORD
