Metadata-Version: 2.1
Name: ania
Version: 1.0.0
Summary: Search, enjoy and download anime in Spanish using the command line.
Home-page: https://github.com/ania-cli/ania
License: GPL-3.0
Author: Miguel Amador
Author-email: miguesdev@gmail.com
Requires-Python: >=3.8,<4.0
Classifier: License :: OSI Approved :: GNU General Public License v3 (GPLv3)
Classifier: Programming Language :: Python :: 3
Classifier: Programming Language :: Python :: 3.8
Classifier: Programming Language :: Python :: 3.9
Classifier: Programming Language :: Python :: 3.10
Classifier: Programming Language :: Python :: 3.11
Requires-Dist: bs4 (==0.0.1)
Requires-Dist: cloudscraper (==1.2.71)
Requires-Dist: flask (==3.0.0)
Requires-Dist: lxml (==4.9.3)
Requires-Dist: termcolor (==2.3.0)
